LICENSE
README.md
fireorm_repository/__init__.py
fireorm_repository/repositories/__init__.py
fireorm_repository/repositories/base.py
fireorm_repository/repositories/interface.py
fireorm_repository/types/__init__.py
fireorm_repository/types/types.py
fireorm_repository-1.0.16.dist-info/LICENSE
fireorm_repository-1.0.16.dist-info/WHEEL
fireorm_repository-1.0.16.dist-info/METADATA
fireorm_repository-1.0.16.dist-info/RECORD
